hexfrost_toolbox-0.1.6.dist-info/METADATA
hexfrost_toolbox-0.1.6.dist-info/WHEEL
hexfrost_toolbox-0.1.6.dist-info/entry_points.txt
hexfrost_toolbox-0.1.6.dist-info/licenses/LICENSE
toolbox/__init__.py
toolbox/auth/enums.py
toolbox/auth/middlewares/fastapi_.py
toolbox/cipher.py
toolbox/decorators.py
toolbox/schemes.py
toolbox/sqlalchemy/__init__.py
toolbox/sqlalchemy/connection.py
toolbox/sqlalchemy/models.py
toolbox/sqlalchemy/repositories.py
toolbox/testing.py
toolbox/utils.py
hexfrost_toolbox-0.1.6.dist-info/RECORD
