Metadata-Version: 2.1
Name: hexfrost-toolbox
Version: 0.1.6
Summary: Open source library with useful utils for fast development
Author-Email: Kaziamov <kaziamov@outlook.com>
Requires-Python: <4.0,>=3.9
Requires-Dist: cryptography>=44.0.3
Requires-Dist: fastapi>=0.115.12
Requires-Dist: pre-commit>=4.2.0
Requires-Dist: psycopg2-binary>=2.9.10
Requires-Dist: pydantic>=2.10.6
Requires-Dist: sqlalchemy>=2.0.40
Requires-Dist: sqlalchemy-utils>=0.41.2
